odoo10_addon_quality_control_stock-10.0.1.0.2-py2.7-nspkg.pth
odoo/addons/quality_control_stock/README.rst
odoo/addons/quality_control_stock/__init__.py
odoo/addons/quality_control_stock/__manifest__.py
odoo/addons/quality_control_stock/data/quality_control_stock_data.xml
odoo/addons/quality_control_stock/i18n/ca.po
odoo/addons/quality_control_stock/i18n/de.po
odoo/addons/quality_control_stock/i18n/el_GR.po
odoo/addons/quality_control_stock/i18n/es.po
odoo/addons/quality_control_stock/i18n/es_AR.po
odoo/addons/quality_control_stock/i18n/es_ES.po
odoo/addons/quality_control_stock/i18n/es_MX.po
odoo/addons/quality_control_stock/i18n/eu.po
odoo/addons/quality_control_stock/i18n/fi.po
odoo/addons/quality_control_stock/i18n/fr.po
odoo/addons/quality_control_stock/i18n/fr_CH.po
odoo/addons/quality_control_stock/i18n/fr_FR.po
odoo/addons/quality_control_stock/i18n/gl.po
odoo/addons/quality_control_stock/i18n/hr.po
odoo/addons/quality_control_stock/i18n/hr_HR.po
odoo/addons/quality_control_stock/i18n/it.po
odoo/addons/quality_control_stock/i18n/nl.po
odoo/addons/quality_control_stock/i18n/nl_NL.po
odoo/addons/quality_control_stock/i18n/pt.po
odoo/addons/quality_control_stock/i18n/pt_BR.po
odoo/addons/quality_control_stock/i18n/quality_control_stock.pot
odoo/addons/quality_control_stock/i18n/ro.po
odoo/addons/quality_control_stock/i18n/ru.po
odoo/addons/quality_control_stock/i18n/sk.po
odoo/addons/quality_control_stock/i18n/sl.po
odoo/addons/quality_control_stock/i18n/tr.po
odoo/addons/quality_control_stock/i18n/tr_TR.po
odoo/addons/quality_control_stock/i18n/vi_VN.po
odoo/addons/quality_control_stock/i18n/zh_CN.po
odoo/addons/quality_control_stock/models/__init__.py
odoo/addons/quality_control_stock/models/qc_inspection.py
odoo/addons/quality_control_stock/models/qc_trigger.py
odoo/addons/quality_control_stock/models/stock_picking.py
odoo/addons/quality_control_stock/models/stock_picking_type.py
odoo10_addon_quality_control_stock-10.0.1.0.2.dist-info/METADATA
odoo10_addon_quality_control_stock-10.0.1.0.2.dist-info/RECORD
odoo10_addon_quality_control_stock-10.0.1.0.2.dist-info/WHEEL
odoo10_addon_quality_control_stock-10.0.1.0.2.dist-info/namespace_packages.txt
odoo10_addon_quality_control_stock-10.0.1.0.2.dist-info/top_level.txt
