Metadata-Version: 2.1
Name: odoo10-addon-quality-control-stock
Version: 10.0.1.0.2
Summary: Quality control - Stock
Home-page: https://github.com/OCA/manufacture/tree/10.0/quality_control_stock
Author: OdooMRP team, AvanzOSC, Serv. Tecnol. Avanzados - Pedro M. Baeza, Agile Business Group, Odoo Community Association (OCA)
Author-email: support@odoo-community.org
License: AGPL-3
Platform: UNKNOWN
Classifier: Programming Language :: Python
Classifier: Framework :: Odoo
Classifier: License :: OSI Approved :: GNU Affero General Public License v3
Requires-Python: ~=2.7
Requires-Dist: odoo10-addon-quality-control
Requires-Dist: odoo (<10.1dev,>=10.0)
